{
  "_class": "oval",
  "booleanOperation": -1,
  "clippingMaskMode": 0,
  "do_objectID": "D1073715-E5CD-42BF-97E4-84C2F50D215D",
  "edited": false,
  "exportOptions": {
    "_class": "exportOptions",
    "exportFormats": [
    ],
    "includedLayerIds": [
    ],
    "layerOptions": 0,
    "shouldTrim": false
  },
  "frame": {
    "_class": "rect",
    "constrainProportions": true,
    "height": 71,
    "width": 71,
    "x": 0.8230625583526034,
    "y": 0
  },
  "hasClippingMask": false,
  "isClosed": true,
  "isFixedToViewport": false,
  "isFlippedHorizontal": false,
  "isFlippedVertical": false,
  "isLocked": false,
  "isVisible": true,
  "layerListExpandedType": 0,
  "name": "Bubble",
  "nameIsFixed": true,
  "pointRadiusBehaviour": 1,
  "points": [
    {
      "_class": "curvePoint",
      "cornerRadius": 0,
      "curveFrom": "{0.77614237489999982, 0.99999999999999978}",
      "curveMode": 2,
      "curveTo": "{0.22385762509999996, 0.99999999999999978}",
      "hasCurveFrom": true,
      "hasCurveTo": true,
      "point": "{0.49999999999999989, 0.99999999999999978}"
    },
    {
      "_class": "curvePoint",
      "cornerRadius": 0,
      "curveFrom": "{0.99999999999999978, 0.22385762509999996}",
      "curveMode": 2,
      "curveTo": "{0.99999999999999978, 0.77614237489999982}",
      "hasCurveFrom": true,
      "hasCurveTo": true,
      "point": "{0.99999999999999978, 0.49999999999999989}"
    },
    {
      "_class": "curvePoint",
      "cornerRadius": 0,
      "curveFrom": "{0.22385762509999996, 0}",
      "curveMode": 2,
      "curveTo": "{0.77614237489999982, 0}",
      "hasCurveFrom": true,
      "hasCurveTo": true,
      "point": "{0.49999999999999989, 0}"
    },
    {
      "_class": "curvePoint",
      "cornerRadius": 0,
      "curveFrom": "{0, 0.77614237489999982}",
      "curveMode": 2,
      "curveTo": "{0, 0.22385762509999996}",
      "hasCurveFrom": true,
      "hasCurveTo": true,
      "point": "{0, 0.49999999999999989}"
    }
  ],
  "resizingConstraint": 63,
  "resizingType": 0,
  "rotation": 0,
  "sharedStyleID": "2F497774-6498-4FA0-9169-CBD5095F736E",
  "shouldBreakMaskChain": false,
  "style": {
    "_class": "style",
    "do_objectID": "71D6A11E-7645-4847-82C9-63952AB9CCCD",
    "endMarkerType": 0,
    "fills": [
      {
        "_class": "fill",
        "color": {
          "_class": "color",
          "alpha": 1,
          "blue": 0.6313725490196077,
          "green": 0.7764705882352941,
          "red": 0.007843137254901926
        },
        "fillType": 0,
        "isEnabled": true,
        "noiseIndex": 0,
        "noiseIntensity": 0,
        "patternFillType": 1,
        "patternTileScale": 1
      }
    ],
    "miterLimit": 10,
    "startMarkerType": 0,
    "windingRule": 1
  },
  "userInfo": {
    "com.animaapp.stc-sketch-plugin": {
      "kModelPropertiesKey": {
        "constraints": {
          "aspectRatio": {
            "constant": 71,
            "enabled": 1,
            "modelID": "constraint_14a023be-0543-4fe4-a82a-cbbe757b6e73",
            "model_class": "ADModelConstraint",
            "model_version": 0.1,
            "multiplier": 71
          },
          "automatic": 1,
          "modelID": "viewConstraints_132f03c9-5c0a-4d8a-a4f4-8869724e78bf",
          "model_class": "ADModelViewConstraints",
          "model_version": 0.1,
          "scaleFactor": 1
        }
      }
    }
  }
}