{
  "_class": "shapePath",
  "booleanOperation": -1,
  "clippingMaskMode": 0,
  "do_objectID": "D129C249-768D-4A1A-BAB4-8AE8A415A8A1",
  "edited": true,
  "exportOptions": {
    "_class": "exportOptions",
    "do_objectID": "1AF485E5-A7C9-4B72-867D-35AC21B67BF4",
    "exportFormats": [
    ],
    "includedLayerIds": [
    ],
    "layerOptions": 0,
    "shouldTrim": false
  },
  "frame": {
    "_class": "rect",
    "constrainProportions": false,
    "do_objectID": "BB26248C-D3CC-4032-9771-2FEA2CB6FBA1",
    "height": 93,
    "width": 93,
    "x": 20,
    "y": 20
  },
  "hasClippingMask": false,
  "isClosed": true,
  "isFixedToViewport": false,
  "isFlippedHorizontal": false,
  "isFlippedVertical": false,
  "isLocked": false,
  "isVisible": true,
  "layerListExpandedType": 1,
  "name": "Shape",
  "nameIsFixed": false,
  "pointRadiusBehaviour": 1,
  "points": [
    {
      "_class": "curvePoint",
      "cornerRadius": 0,
      "curveFrom": "{1.0000000000000009, 0}",
      "curveMode": 1,
      "curveTo": "{1.0000000000000009, 0}",
      "hasCurveFrom": false,
      "hasCurveTo": false,
      "point": "{1.0000000000000009, 0}"
    },
    {
      "_class": "curvePoint",
      "cornerRadius": 0,
      "curveFrom": "{0.50000000000000044, 1}",
      "curveMode": 1,
      "curveTo": "{0.50000000000000044, 1}",
      "hasCurveFrom": false,
      "hasCurveTo": false,
      "point": "{0.50000000000000044, 1}"
    },
    {
      "_class": "curvePoint",
      "cornerRadius": 0,
      "curveFrom": "{0, 7.9301644616082612e-17}",
      "curveMode": 1,
      "curveTo": "{0, 7.9301644616082612e-17}",
      "hasCurveFrom": false,
      "hasCurveTo": false,
      "point": "{0, 7.9301644616082612e-17}"
    }
  ],
  "resizingConstraint": 63,
  "resizingType": 0,
  "rotation": 0,
  "shouldBreakMaskChain": false,
  "style": {
    "_class": "style",
    "do_objectID": "BBB3E3C9-DD9C-4ACF-8C90-9B12BB7CA7B1",
    "endMarkerType": 0,
    "fills": [
      {
        "_class": "fill",
        "color": {
          "_class": "color",
          "alpha": 1,
          "blue": 1,
          "green": 1,
          "red": 1
        },
        "fillType": 0,
        "isEnabled": true,
        "noiseIndex": 0,
        "noiseIntensity": 0,
        "patternFillType": 1,
        "patternTileScale": 1
      }
    ],
    "miterLimit": 10,
    "startMarkerType": 0,
    "windingRule": 0
  },
  "userInfo": {
    "com.animaapp.stc-sketch-plugin": {
      "kModelPropertiesKey": {
      }
    }
  }
}