{
  "_class": "symbolInstance",
  "booleanOperation": 0,
  "clippingMaskMode": 0,
  "do_objectID": "120905E6-B0D0-452E-B7B6-0132D47F8BB7",
  "exportOptions": {
    "_class": "exportOptions",
    "exportFormats": [
    ],
    "includedLayerIds": [
    ],
    "layerOptions": 0,
    "shouldTrim": false
  },
  "frame": {
    "_class": "rect",
    "constrainProportions": false,
    "height": 12,
    "width": 360,
    "x": 0,
    "y": 72
  },
  "hasClippingMask": false,
  "horizontalSpacing": 0,
  "isFixedToViewport": false,
  "isFlippedHorizontal": false,
  "isFlippedVertical": false,
  "isLocked": false,
  "isVisible": true,
  "layerListExpandedType": 1,
  "name": "07. Sliders / Regular",
  "nameIsFixed": true,
  "overrideValues": [
    {
      "_class": "overrideValue",
      "overrideName": "58F927CC-FD59-4251-8958-2C6BF5F81355_symbolID",
      "value": "75293F57-6995-41E7-93C8-C07F78F60494"
    },
    {
      "_class": "overrideValue",
      "do_objectID": "51CF536D-B3F0-4F4D-A01A-77A7466758D7",
      "overrideName": "58F927CC-FD59-4251-8958-2C6BF5F81355/4F70ACDA-B15F-46B9-A257-96695D21B832_symbolID",
      "value": "201349A9-5DC2-4105-BE40-D81DCB2E711C"
    },
    {
      "_class": "overrideValue",
      "do_objectID": "41F871C1-3FC0-43F1-96ED-C17C8A9FCC55",
      "overrideName": "58F927CC-FD59-4251-8958-2C6BF5F81355/C2C8E175-856A-40BB-B128-57EA41F1BE01_symbolID",
      "value": "08FBD53C-3FA2-413B-9A8B-387C4DEBA949"
    }
  ],
  "resizingConstraint": 63,
  "resizingType": 0,
  "rotation": 0,
  "scale": 1,
  "shouldBreakMaskChain": false,
  "style": {
    "_class": "style",
    "endMarkerType": 0,
    "miterLimit": 10,
    "startMarkerType": 0,
    "windingRule": 1
  },
  "symbolID": "08369C60-8241-4148-8864-0E73D0917AD3",
  "verticalSpacing": 0
}