{
  "_class": "text",
  "attributedString": {
    "_class": "attributedString",
    "attributes": [
      {
        "_class": "stringAttribute",
        "attributes": {
          "MSAttributedStringColorAttribute": {
            "_class": "color",
            "alpha": 1,
            "blue": 0.07058823529,
            "green": 0.03921568627,
            "red": 0
          },
          "MSAttributedStringFontAttribute": {
            "_class": "fontDescriptor",
            "attributes": {
              "name": "Montserrat-Regular",
              "size": 32
            }
          },
          "MSAttributedStringTextTransformAttribute": 0,
          "kerning": 0.1000000014901161,
          "paragraphStyle": {
            "_class": "paragraphStyle",
            "alignment": 0,
            "maximumLineHeight": 42,
            "minimumLineHeight": 42
          }
        },
        "length": 10,
        "location": 0
      }
    ],
    "string": "H2 Heading"
  },
  "automaticallyDrawOnUnderlyingPath": false,
  "booleanOperation": 0,
  "clippingMaskMode": 0,
  "do_objectID": "5C9DB83D-885C-4144-A1C3-4FA3391DD37F",
  "dontSynchroniseWithSymbol": false,
  "exportOptions": {
    "_class": "exportOptions",
    "do_objectID": "555BB5A3-EE41-4819-9B42-068C0F028390",
    "exportFormats": [
    ],
    "includedLayerIds": [
    ],
    "layerOptions": 0,
    "shouldTrim": false
  },
  "frame": {
    "_class": "rect",
    "constrainProportions": false,
    "do_objectID": "D587E315-B570-4257-9F06-8153E9793785",
    "height": 42,
    "width": 192,
    "x": 0,
    "y": 0
  },
  "glyphBounds": "{{3, 8}, {186, 31}}",
  "hasClippingMask": false,
  "isFixedToViewport": false,
  "isFlippedHorizontal": false,
  "isFlippedVertical": false,
  "isLocked": false,
  "isVisible": true,
  "layerListExpandedType": 0,
  "lineSpacingBehaviour": 2,
  "name": "H2 / Roboto / Left / Dark",
  "nameIsFixed": false,
  "resizingConstraint": 41,
  "resizingType": 0,
  "rotation": 0,
  "sharedStyleID": "37DFBA4B-3671-4DC5-8F6E-B0B384B422A1",
  "shouldBreakMaskChain": false,
  "style": {
    "_class": "style",
    "do_objectID": "598479BA-DCE6-4DC7-BCDD-7AA091D42513",
    "endMarkerType": 0,
    "miterLimit": 10,
    "startMarkerType": 0,
    "textStyle": {
      "_class": "textStyle",
      "do_objectID": "86689865-9198-419A-B17A-6C672D30EAB8",
      "encodedAttributes": {
        "MSAttributedStringColorAttribute": {
          "_class": "color",
          "alpha": 1,
          "blue": 0.07058823529,
          "green": 0.03921568627,
          "red": 0
        },
        "MSAttributedStringFontAttribute": {
          "_class": "fontDescriptor",
          "attributes": {
            "name": "Montserrat-Regular",
            "size": 32
          }
        },
        "MSAttributedStringTextTransformAttribute": 0,
        "kerning": 0.1000000014901161,
        "paragraphStyle": {
          "_class": "paragraphStyle",
          "alignment": 0,
          "maximumLineHeight": 42,
          "minimumLineHeight": 42
        }
      },
      "verticalAlignment": 0
    },
    "windingRule": 1
  },
  "textBehaviour": 0,
  "userInfo": {
    "com.animaapp.stc-sketch-plugin": {
      "kModelPropertiesKey": {
        "isAutoWidth": 1
      }
    }
  }
}