{
  "_class": "group",
  "booleanOperation": -1,
  "clippingMaskMode": 0,
  "do_objectID": "1327714D-A6D1-4B21-87B7-9CF9DF3929A0",
  "exportOptions": {
    "_class": "exportOptions",
    "do_objectID": "8AEF996A-9934-47C9-9179-DB400EC36AFB",
    "exportFormats": [
    ],
    "includedLayerIds": [
    ],
    "layerOptions": 0,
    "shouldTrim": false
  },
  "frame": {
    "_class": "rect",
    "constrainProportions": false,
    "do_objectID": "32DC811B-479A-4F10-9FC2-9A9E755C8BBD",
    "height": 28,
    "width": 200,
    "x": 164,
    "y": 947
  },
  "hasClickThrough": false,
  "hasClippingMask": false,
  "isFixedToViewport": false,
  "isFlippedHorizontal": false,
  "isFlippedVertical": false,
  "isLocked": false,
  "isVisible": true,
  "layerListExpandedType": 0,
  "layers": [
    {
      "class": "text",
      "id": "D285ECAA-7C59-4C6A-B437-632B3A6AA162"
    }
  ],
  "name": "✱ / Text / Body 1 / White / High Emphasis / Left",
  "nameIsFixed": false,
  "resizingConstraint": 63,
  "resizingType": 0,
  "rotation": 0,
  "shouldBreakMaskChain": false,
  "style": {
    "_class": "style",
    "do_objectID": "4776FCE3-D5A0-4082-9B79-52BE9BB3C1BF",
    "endMarkerType": 0,
    "miterLimit": 10,
    "startMarkerType": 0,
    "windingRule": 1
  },
  "userInfo": {
    "com.animaapp.stc-sketch-plugin": {
      "kModelPropertiesKey": {
      }
    }
  }
}