{
  "_class": "symbolInstance",
  "booleanOperation": 0,
  "clippingMaskMode": 0,
  "do_objectID": "F29EFF56-2D13-497E-B080-915EBCA37EE2",
  "exportOptions": {
    "_class": "exportOptions",
    "do_objectID": "F67F18D8-1CEE-475B-9D1B-995E82E1D203",
    "exportFormats": [
    ],
    "includedLayerIds": [
    ],
    "layerOptions": 0,
    "shouldTrim": false
  },
  "frame": {
    "_class": "rect",
    "constrainProportions": false,
    "do_objectID": "6A293015-B77C-4B6F-8904-BB758EA63397",
    "height": 28,
    "width": 272,
    "x": 72,
    "y": 40
  },
  "hasClippingMask": false,
  "horizontalSpacing": 0,
  "isFixedToViewport": false,
  "isFlippedHorizontal": false,
  "isFlippedVertical": false,
  "isLocked": false,
  "isVisible": true,
  "layerListExpandedType": 0,
  "name": "Title",
  "nameIsFixed": true,
  "overrideValues": [
    {
      "_class": "overrideValue",
      "do_objectID": "4279B7C3-FC22-49CE-BAB4-575BE4CEFB3F",
      "overrideName": "80C91616-A62D-4E64-9333-C3CF5728FBBD_stringValue",
      "value": "Title ▾"
    }
  ],
  "resizingConstraint": 34,
  "resizingType": 0,
  "rotation": 0,
  "scale": 1,
  "shouldBreakMaskChain": false,
  "style": {
    "_class": "style",
    "do_objectID": "C43BAD50-E419-40F7-A713-7B9CF1636112",
    "endMarkerType": 0,
    "miterLimit": 10,
    "startMarkerType": 0,
    "windingRule": 1
  },
  "symbolID": "46511E89-10FE-41AA-80EC-8D7CFF750985",
  "userInfo": {
    "com.animaapp.stc-sketch-plugin": {
      "kModelPropertiesKey": {
      }
    }
  },
  "verticalSpacing": 0
}