{
  "_class": "shapeGroup",
  "booleanOperation": 0,
  "clippingMaskMode": 0,
  "do_objectID": "7ED8A3B0-680F-48E0-B59D-D2D791716EE0",
  "exportOptions": {
    "_class": "exportOptions",
    "exportFormats": [
    ],
    "includedLayerIds": [
    ],
    "layerOptions": 0,
    "shouldTrim": false
  },
  "frame": {
    "_class": "rect",
    "constrainProportions": true,
    "height": 16.99999999999994,
    "width": 22,
    "x": 1,
    "y": 4.000000000000057
  },
  "hasClickThrough": false,
  "hasClippingMask": true,
  "isFixedToViewport": false,
  "isFlippedHorizontal": false,
  "isFlippedVertical": false,
  "isLocked": false,
  "isVisible": true,
  "layerListExpandedType": 0,
  "layers": [
    {
      "class": "shapePath",
      "id": "D09B2E56-5A02-420F-9DC2-D3456460C772"
    },
    {
      "class": "shapePath",
      "id": "97B026F7-D16C-4E13-B4F7-61EA5FA21FB6"
    },
    {
      "class": "shapePath",
      "id": "8B5F9A99-C2C8-45C6-ABD3-0C2D40CC4471"
    }
  ],
  "name": "↳Color",
  "nameIsFixed": true,
  "resizingConstraint": 63,
  "resizingType": 0,
  "rotation": 0,
  "sharedStyleID": "7506F2DB-3127-45F1-BD79-82516071B13C",
  "shouldBreakMaskChain": false,
  "style": {
    "_class": "style",
    "do_objectID": "10E5276E-F496-4AB6-9F4A-B8976F94C80C",
    "endMarkerType": 0,
    "fills": [
      {
        "_class": "fill",
        "color": {
          "_class": "color",
          "alpha": 1,
          "blue": 0.03137254901960784,
          "green": 0.4549019607843138,
          "red": 0.9490196078431372
        },
        "fillType": 0,
        "isEnabled": true,
        "noiseIndex": 0,
        "noiseIntensity": 0,
        "patternFillType": 1,
        "patternTileScale": 1
      }
    ],
    "miterLimit": 10,
    "startMarkerType": 0,
    "windingRule": 1
  },
  "windingRule": 1
}