{
  "_class": "sharedStyle",
  "do_objectID": "BD3A95FD-611A-4088-8B43-BCF8E7669518",
  "name": "Subheader / Left / Dark",
  "value": {
    "_class": "style",
    "endMarkerType": 0,
    "miterLimit": 10,
    "startMarkerType": 0,
    "textStyle": {
      "_class": "textStyle",
      "encodedAttributes": {
        "MSAttributedStringColorAttribute": {
          "_class": "color",
          "alpha": 1,
          "blue": 0.3098039215686275,
          "green": 0.2784313725490196,
          "red": 0.2156862745098039
        },
        "MSAttributedStringFontAttribute": {
          "_class": "fontDescriptor",
          "attributes": {
            "name": "OpenSans-Light",
            "size": 18
          }
        },
        "paragraphStyle": {
          "_class": "paragraphStyle",
          "alignment": 0,
          "allowsDefaultTighteningForTruncation": 0,
          "maximumLineHeight": 25,
          "minimumLineHeight": 25,
          "tighteningFactorForTruncation": 0.05
        }
      },
      "verticalAlignment": 0
    },
    "windingRule": 1
  }
}