{
  "_class": "group",
  "booleanOperation": 0,
  "clippingMaskMode": 0,
  "do_objectID": "BE4967F4-697C-435D-A702-362B6BAA43C1",
  "exportOptions": {
    "_class": "exportOptions",
    "exportFormats": [
    ],
    "includedLayerIds": [
    ],
    "layerOptions": 0,
    "shouldTrim": false
  },
  "frame": {
    "_class": "rect",
    "constrainProportions": false,
    "height": 56,
    "width": 336,
    "x": 12,
    "y": 68
  },
  "hasClickThrough": false,
  "hasClippingMask": false,
  "isFixedToViewport": false,
  "isFlippedHorizontal": false,
  "isFlippedVertical": false,
  "isLocked": false,
  "isVisible": true,
  "layerListExpandedType": 0,
  "layers": [
    {
      "class": "rectangle",
      "id": "8825324E-0233-43D7-86B6-1B90809B59D3"
    },
    {
      "class": "text",
      "id": "03AA9881-4071-41DA-96D3-EF8B33B80B98"
    },
    {
      "class": "text",
      "id": "E45D6CAD-D2F1-4728-8ECF-6A83174C212F"
    }
  ],
  "name": "87%",
  "nameIsFixed": true,
  "resizingConstraint": 63,
  "resizingType": 0,
  "rotation": 0,
  "shouldBreakMaskChain": false,
  "style": {
    "_class": "style",
    "endMarkerType": 0,
    "miterLimit": 10,
    "startMarkerType": 0,
    "windingRule": 1
  }
}