{
  "_class": "group",
  "booleanOperation": 0,
  "clippingMaskMode": 0,
  "do_objectID": "B6838EF3-16BE-48FE-8B9F-01EC7B3DC360",
  "exportOptions": {
    "_class": "exportOptions",
    "exportFormats": [
    ],
    "includedLayerIds": [
    ],
    "layerOptions": 0,
    "shouldTrim": false
  },
  "frame": {
    "_class": "rect",
    "constrainProportions": false,
    "height": 347,
    "width": 605,
    "x": 100,
    "y": 4223
  },
  "groupLayout": {
    "_class": "MSImmutableFreeformGroupLayout"
  },
  "hasClickThrough": false,
  "hasClippingMask": false,
  "isFixedToViewport": false,
  "isFlippedHorizontal": false,
  "isFlippedVertical": false,
  "isLocked": false,
  "isVisible": true,
  "layerListExpandedType": 0,
  "layers": [
    {
      "class": "group",
      "id": "9CFC3EB0-8D4B-4C20-8BE3-833A75F73EF4"
    },
    {
      "class": "group",
      "id": "FA74B8E1-FD82-42D0-BB55-54D9F82C9956"
    },
    {
      "class": "group",
      "id": "274FBFAE-3AF1-4311-8968-B2FFB8ACF794"
    },
    {
      "class": "text",
      "id": "AD09D4A3-3013-4098-BA21-25D560981458"
    }
  ],
  "name": "Chips",
  "nameIsFixed": true,
  "resizingConstraint": 63,
  "resizingType": 0,
  "rotation": 0,
  "shouldBreakMaskChain": false,
  "style": {
    "_class": "style",
    "endMarkerType": 0,
    "miterLimit": 10,
    "startMarkerType": 0,
    "windingRule": 1
  },
  "userInfo": {
    "com.animaapp.stc-sketch-plugin": {
      "kModelPropertiesKey": {
      }
    }
  }
}