{
  "_class": "symbolInstance",
  "booleanOperation": 0,
  "clippingMaskMode": 0,
  "do_objectID": "7432FA3E-3591-46F3-B616-8ACFD1FE1B95",
  "exportOptions": {
    "_class": "exportOptions",
    "exportFormats": [
    ],
    "includedLayerIds": [
    ],
    "layerOptions": 0,
    "shouldTrim": false
  },
  "frame": {
    "_class": "rect",
    "constrainProportions": false,
    "height": 48,
    "width": 116,
    "x": 0,
    "y": 68
  },
  "hasClippingMask": false,
  "horizontalSpacing": 0,
  "isFixedToViewport": false,
  "isFlippedHorizontal": false,
  "isFlippedVertical": false,
  "isLocked": false,
  "isVisible": true,
  "layerListExpandedType": 1,
  "name": "03. Buttons / Raised",
  "nameIsFixed": true,
  "overrideValues": [
    {
      "_class": "overrideValue",
      "do_objectID": "676F31FE-0618-4F94-9669-9CF763E7BC52",
      "overrideName": "E3BC27CD-ABE9-46DC-A212-93A3D0359F0A_symbolID",
      "value": "04EDE26F-69EF-410B-9DAF-28615D9BDADE"
    },
    {
      "_class": "overrideValue",
      "do_objectID": "5DBFC78B-4AA7-4651-9414-919BC25B23BF",
      "overrideName": "E3BC27CD-ABE9-46DC-A212-93A3D0359F0A/24140490-A97B-48BA-92BD-021F54F1D669/3D51C7F7-1AE1-4313-B785-E5D49B76BD8C_stringValue",
      "value": "Focused"
    }
  ],
  "resizingConstraint": 63,
  "resizingType": 0,
  "rotation": 0,
  "scale": 1,
  "shouldBreakMaskChain": false,
  "style": {
    "_class": "style",
    "endMarkerType": 0,
    "miterLimit": 10,
    "startMarkerType": 0,
    "windingRule": 1
  },
  "symbolID": "72E22E58-D4E9-4685-A22A-BF7EE19C9347",
  "verticalSpacing": 0
}