{
  "_class": "group",
  "booleanOperation": -1,
  "clippingMaskMode": 0,
  "do_objectID": "235F850A-E225-4092-A738-E90FC1A61BE3",
  "exportOptions": {
    "_class": "exportOptions",
    "do_objectID": "BEAA935E-64A8-4EE0-832B-7FD358C96EE9",
    "exportFormats": [
    ],
    "includedLayerIds": [
    ],
    "layerOptions": 0,
    "shouldTrim": false
  },
  "frame": {
    "_class": "rect",
    "constrainProportions": false,
    "do_objectID": "0DED3E44-6348-4F1B-963F-C553937EF2A4",
    "height": 28,
    "width": 120,
    "x": 1179,
    "y": 2003
  },
  "hasClickThrough": false,
  "hasClippingMask": false,
  "isFixedToViewport": false,
  "isFlippedHorizontal": false,
  "isFlippedVertical": false,
  "isLocked": false,
  "isVisible": true,
  "layerListExpandedType": 0,
  "layers": [
    {
      "class": "text",
      "id": "90598A83-95DB-46B9-9D6F-3F1E099E73F5"
    }
  ],
  "name": "✱ / Text / Body 1 / Black / High Emphasis / Left",
  "nameIsFixed": false,
  "resizingConstraint": 63,
  "resizingType": 0,
  "rotation": 0,
  "shouldBreakMaskChain": false,
  "style": {
    "_class": "style",
    "do_objectID": "63047628-E114-412A-B8D4-170BFA97EBA9",
    "endMarkerType": 0,
    "miterLimit": 10,
    "startMarkerType": 0,
    "windingRule": 1
  },
  "userInfo": {
    "com.animaapp.stc-sketch-plugin": {
      "kModelPropertiesKey": {
      }
    }
  }
}